{
    "Ar36": {
        "error": 0.0005245588690591947,
        "error_type": "SEM",
        "filter_outliers_dict": {
            "filter_outliers": true,
            "iterations": 1,
            "std_devs": 3,
            "use_iqr_filtering": false,
            "use_standard_deviation_filtering": false
        },
        "fit": "parabolic",
        "fn": 340,
        "include_baseline_error": true,
        "n": 340,
        "outlier_excluded": [],
        "reviewed": true,
        "user_excluded": [],
        "value": 0.02368415518632424
    },
    "Ar37": {
        "error": 0.0174247031171464,
        "error_type": "SEM",
        "filter_outliers_dict": {
            "filter_outliers": true,
            "iterations": 1,
            "std_devs": 3,
            "use_iqr_filtering": false,
            "use_standard_deviation_filtering": false
        },
        "fit": "linear",
        "fn": 339,
        "include_baseline_error": true,
        "n": 340,
        "outlier_excluded": [
            93
        ],
        "reviewed": true,
        "user_excluded": [],
        "value": 0.05789531913324143
    },
    "Ar38": {
        "error": 0.005357077094012437,
        "error_type": "SEM",
        "filter_outliers_dict": {
            "filter_outliers": true,
            "iterations": 1,
            "std_devs": 3,
            "use_iqr_filtering": false,
            "use_standard_deviation_filtering": false
        },
        "fit": "linear",
        "fn": 337,
        "include_baseline_error": true,
        "n": 340,
        "outlier_excluded": [
            104,
            335,
            87
        ],
        "reviewed": true,
        "user_excluded": [],
        "value": 0.7857686309696987
    },
    "Ar39": {
        "error": 0.02179168309820323,
        "error_type": "SEM",
        "filter_outliers_dict": {
            "filter_outliers": true,
            "iterations": 1,
            "std_devs": 3,
            "use_iqr_filtering": false,
            "use_standard_deviation_filtering": false
        },
        "fit": "parabolic",
        "fn": 339,
        "include_baseline_error": true,
        "n": 340,
        "outlier_excluded": [
            273
        ],
        "reviewed": true,
        "user_excluded": [],
        "value": 56.74886638816243
    },
    "Ar40": {
        "error": 0.06281847347871704,
        "error_type": "SEM",
        "filter_outliers_dict": {
            "filter_outliers": true,
            "iterations": 1,
            "std_devs": 3,
            "use_iqr_filtering": false,
            "use_standard_deviation_filtering": false
        },
        "fit": "parabolic",
        "fn": 336,
        "include_baseline_error": true,
        "n": 340,
        "outlier_excluded": [
            259,
            105,
            106,
            258
        ],
        "reviewed": true,
        "user_excluded": [],
        "value": 383.5012144491326
    }
}